v6e/__init__.py
v6e/exceptions.py
v6e/py.typed
v6e/types/base.py
v6e/types/boolean.py
v6e/types/calendar.py
v6e/types/comparable.py
v6e/types/dict.py
v6e/types/list.py
v6e/types/numbers.py
v6e/types/path.py
v6e/types/result.py
v6e/types/string.py
v6e/types/struct.py
v6e/types/utils.py
v6e-0.1.18.dist-info/METADATA
v6e-0.1.18.dist-info/WHEEL
v6e-0.1.18.dist-info/licenses/LICENSE
v6e-0.1.18.dist-info/RECORD
