Metadata-Version: 2.4
Name: v6e
Version: 0.1.18
Summary: A simple, type-safe, and extensible Python parsing and validation framework
Project-URL: Documentation, https://github.com/danimelchor/v6e
Project-URL: Homepage, https://github.com/danimelchor/v6e
Project-URL: Repository, https://github.com/danimelchor/v6e
Project-URL: Issues, https://github.com/danimelchor/v6e/issues
Author-email: Daniel Melchor <dmelchor@pm.me>
License-Expression: MIT
License-File: LICENSE
Keywords: check,data,parser,validate,validation
Requires-Python: <3.13,~=3.11
Requires-Dist: python-dateutil>=2.9.0
Requires-Dist: typing-extensions>=4.12.2
Provides-Extra: dev
Requires-Dist: pyright>=1.1.394; extra == 'dev'
Requires-Dist: pytest>=8.3.4; extra == 'dev'
Requires-Dist: ruff>=0.9.7; extra == 'dev'
